{
  "tournament": "Kumpoo Tervasulan Eliitti 2025",
  "name": "Boys' Singles U11",
  "code": "BS U11",
  "category": "Junior",
  "sheet": "BS U11-Main Draw",
  "draw_type": "main_draw",
  "format": "round_robin",
  "players": [
    {
      "position": 1,
      "name": "Luka Heikkil채",
      "club": "YlTe",
      "seed": "1",
      "status": null
    },
    {
      "position": 2,
      "name": "Siwei Lucas Qiu",
      "club": "ParBa",
      "seed": "2",
      "status": null
    },
    {
      "position": 3,
      "name": "Ann Nelson",
      "club": "TeSu",
      "seed": null,
      "status": null
    },
    {
      "position": 4,
      "name": "Ashlyn Jinu",
      "club": "TeSu",
      "seed": null,
      "status": null
    }
  ],
  "matches": [
    {
      "match": 1,
      "player1": "Luka Heikkil채",
      "player2": "Siwei Lucas Qiu"
    },
    {
      "match": 2,
      "player1": "Luka Heikkil채",
      "player2": "Ann Nelson"
    },
    {
      "match": 3,
      "player1": "Luka Heikkil채",
      "player2": "Ashlyn Jinu"
    },
    {
      "match": 4,
      "player1": "Siwei Lucas Qiu",
      "player2": "Ann Nelson"
    },
    {
      "match": 5,
      "player1": "Siwei Lucas Qiu",
      "player2": "Ashlyn Jinu"
    },
    {
      "match": 6,
      "player1": "Ann Nelson",
      "player2": "Ashlyn Jinu"
    }
  ],
  "clubs": [
    "ParBa",
    "TeSu",
    "YlTe"
  ]
}